{"meta":{"source":"Goals Dashboard Source","lastUpdated":"2026-05-12T17:34:49.6584610Z"},"monthlyNewPremium":[{"@odata.etag":"","ItemInternalId":"87c9a605-cf9c-4882-9ed1-1d6527786eec","Agent":"Mary","Amount":"0"},{"@odata.etag":"","ItemInternalId":"98fb5553-1a8d-4b09-9bbe-a7278a04cb90","Agent":"Nesida","Amount":"40438.4"},{"@odata.etag":"","ItemInternalId":"fb27a559-4115-4679-8bda-80a5042cdde7","Agent":"Austin","Amount":"21707.83"},{"@odata.etag":"","ItemInternalId":"aa754393-1882-4f92-9eaf-423f852f630b","Agent":"Gaby","Amount":"267"},{"@odata.etag":"","ItemInternalId":"5d2d79d1-9ea3-4e1b-b5e6-9e79f273fbd3","Agent":"Richar","Amount":"0"},{"@odata.etag":"","ItemInternalId":"2aa5bfb0-1fa9-469f-a969-70ecfb1be4e3","Agent":"Isaac","Amount":"654.21"},{"@odata.etag":"","ItemInternalId":"b154ea13-c3ac-47fc-8a73-d4abe42c95bc","Agent":"Richard L","Amount":"0"},{"@odata.etag":"","ItemInternalId":"b3ea4085-6740-4cea-b1b2-1d6c50d38e79","Agent":"Total","Amount":"63067.44"}],"weeklyIncentives":[{"@odata.etag":"","ItemInternalId":"86b51fea-d063-4ac5-8769-0c569babd49b","Policies":"23","StatusMessage":"Keep selling... 12 more to Level 1!"}],"goalLevels":[{"@odata.etag":"","ItemInternalId":"813105d3-bbed-4729-8881-34fde30389ef","Level":"1","Threshold":"35 - Activated ⚡","Label":"Most New Policies → sm spin","Unlocked":"False"},{"@odata.etag":"","ItemInternalId":"0c286c1f-d643-43d7-ab29-ec3f78157ab1","Level":"2a","Threshold":"40 - Charged Up 🔋","Label":"➕ Drawing for sm spin (qualify with 5+ new policies, 1 entry per person)","Unlocked":"False"},{"@odata.etag":"","ItemInternalId":"e2ab26e8-a91a-40c9-824e-4e469bb30390","Level":"2b","Threshold":"40 - Pizza Power 🍕","Label":"➕ Pizza for the Office","Unlocked":"False"},{"@odata.etag":"","ItemInternalId":"f4a5f51f-79a8-4d08-ad77-f2e7be52976f","Level":"3","Threshold":"45 - Supercharged ⚡","Label":"➕ McDonald's/Chick-Fil-A Breakfast OR Upgraded Lunch","Unlocked":"False"},{"@odata.etag":"","ItemInternalId":"8897686e-e961-415a-8ae7-7e0026b49a53","Level":"4","Threshold":"50 - Overdrive 🚀","Label":"➕ Drawing for sm spin (anyone who sold a new policy, 1 entry per person)","Unlocked":"False"},{"@odata.etag":"","ItemInternalId":"63cce84a-c236-40f2-a856-362266e6b0c4","Level":"5","Threshold":"55 - Maximum Power 💥","Label":"ALL OF THE ABOVE ➕ Most New gets 🎗️🎗️🎗️LARGE SPIN 🎰 (replaces sm spin)","Unlocked":"False"}],"weeklyAgentBreakdown":[{"@odata.etag":"","ItemInternalId":"86a8a525-92e8-40f5-b0bc-34a1c593b310","Rank":"0","Agent":"Mary","Policies":"0","Premium":"0"},{"@odata.etag":"","ItemInternalId":"7d615a85-648a-47dd-98c3-dab726e2f053","Rank":"1","Agent":"Nesida","Policies":"12","Premium":"23330.1"},{"@odata.etag":"","ItemInternalId":"f143bb60-0949-4249-a457-6eab7799a87d","Rank":"2","Agent":"Austin","Policies":"11","Premium":"19226.83"},{"@odata.etag":"","ItemInternalId":"3f1231b3-0b7b-41a1-bf3e-01416f4486ea","Rank":"0","Agent":"Gaby","Policies":"0","Premium":"0"},{"@odata.etag":"","ItemInternalId":"dcfc4c04-3b7c-41f0-a78f-c21abf750cd0","Rank":"0","Agent":"Richar","Policies":"0","Premium":"0"},{"@odata.etag":"","ItemInternalId":"cf9c3f64-e9c9-42bf-9bcd-bbd20ec37ac3","Rank":"0","Agent":"Isaac","Policies":"0","Premium":"0"},{"@odata.etag":"","ItemInternalId":"fd519648-8ab7-4b92-9429-4c809907a67f","Rank":"0","Agent":"Richard L","Policies":"0","Premium":"0"}],"drawings":[{"@odata.etag":"","ItemInternalId":"9a7a6970-bc02-4ade-aba5-3799b84c7493","Type":"📋 5+ POLICIES DRAWING (Unlocks at Level 2a ➡️ 40 policies)","Locked":"","Required":"","Agent":"❌ LOCKED - Need 17 more policies to unlock"},{"@odata.etag":"","ItemInternalId":"65eeedec-91d2-47b3-ad89-49b087e18b4e","Type":"fivePlus","Locked":"True","Required":"40","Agent":"Mary"},{"@odata.etag":"","ItemInternalId":"10cdbf0e-d9e7-4e98-99b2-3afcfc4aa414","Type":"fivePlus","Locked":"True","Required":"40","Agent":"Nesida"},{"@odata.etag":"","ItemInternalId":"a2620937-8b1c-4d7d-892c-208771e6e2f0","Type":"fivePlus","Locked":"True","Required":"40","Agent":"Austin"},{"@odata.etag":"","ItemInternalId":"09766769-17e6-4b7f-85de-c5ccc15237d4","Type":"fivePlus","Locked":"True","Required":"40","Agent":"Gaby"},{"@odata.etag":"","ItemInternalId":"0030667e-36b0-404f-96c0-7748c4254819","Type":"fivePlus","Locked":"True","Required":"40","Agent":"Richar"},{"@odata.etag":"","ItemInternalId":"65526f50-795d-48eb-bc60-13a2863e13f3","Type":"fivePlus","Locked":"True","Required":"40","Agent":"Isaac"},{"@odata.etag":"","ItemInternalId":"7ee1cd9f-0b8a-46bc-9ae2-75bf10cabbe4","Type":"fivePlus","Locked":"True","Required":"40","Agent":"Richard L"},{"@odata.etag":"","ItemInternalId":"c6643cfb-f71c-4c44-a09d-234b31cfc33b","Type":"📋 1+ POLICIES DRAWING (Unlocks at Level 4 ➡️ 50 policies)","Locked":"","Required":"","Agent":"❌ LOCKED - Need 27 more policies to unlock"},{"@odata.etag":"","ItemInternalId":"99efc110-dde9-4bf3-8133-1a051692b911","Type":"onePlus","Locked":"True","Required":"50","Agent":"Mary"},{"@odata.etag":"","ItemInternalId":"9d46a073-6ef2-4c95-8170-bcd2fc66930c","Type":"onePlus","Locked":"True","Required":"50","Agent":"Nesida"},{"@odata.etag":"","ItemInternalId":"2ae484f8-79dc-4ee1-851d-ee62ba91a823","Type":"onePlus","Locked":"True","Required":"50","Agent":"Austin"},{"@odata.etag":"","ItemInternalId":"63aeb47b-12ef-4fdd-8dea-97f3a3f7b30c","Type":"onePlus","Locked":"True","Required":"50","Agent":"Gaby"},{"@odata.etag":"","ItemInternalId":"054b06da-c0b2-4142-ae7f-62d4ca21794d","Type":"onePlus","Locked":"True","Required":"50","Agent":"Richar"},{"@odata.etag":"","ItemInternalId":"809919e7-3c45-4228-a35e-8cb78803c874","Type":"onePlus","Locked":"True","Required":"50","Agent":"Isaac"},{"@odata.etag":"","ItemInternalId":"4f4c7789-7197-4e78-bdf0-7ed2b07600be","Type":"onePlus","Locked":"True","Required":"50","Agent":"Richard L"}]}