{"meta":{"source":"Goals Dashboard Source","lastUpdated":"2026-04-28T09:57:15.2783881Z"},"monthlyNewPremium":[{"@odata.etag":"","ItemInternalId":"b1922ffd-66c8-4bbd-ba3c-5fca4b909569","Agent":"Mary","Amount":"0"},{"@odata.etag":"","ItemInternalId":"e87b0f67-c0af-4e2a-ae26-e92e35aae1f6","Agent":"Nesida","Amount":"60750.75"},{"@odata.etag":"","ItemInternalId":"18eb770b-4fd7-4092-892e-8e3c25195bf0","Agent":"Austin","Amount":"53261.16"},{"@odata.etag":"","ItemInternalId":"86916ffc-1ca6-4f3a-8371-8e7701da2afb","Agent":"Gaby","Amount":"66480.51"},{"@odata.etag":"","ItemInternalId":"4dd70872-7310-4d29-94b1-bbf39d227cff","Agent":"Richar","Amount":"679"},{"@odata.etag":"","ItemInternalId":"ec0c1c65-7c03-4648-adb5-1d6992785ef0","Agent":"Isaac","Amount":"9101.19"},{"@odata.etag":"","ItemInternalId":"9a89b1e0-29a3-41e9-a745-6779484f42c8","Agent":"Richard L","Amount":"21729.86"},{"@odata.etag":"","ItemInternalId":"c59b1ccf-b8c1-4296-a93a-f2587211e865","Agent":"Keylis","Amount":"11730.67"},{"@odata.etag":"","ItemInternalId":"af6a4ab6-e723-424a-b8ca-74eec6ee3fc8","Agent":"Total","Amount":"223733.14"}],"weeklyIncentives":[{"@odata.etag":"","ItemInternalId":"22df6408-656d-4694-a43d-985190c0bdad","Policies":"41","StatusMessage":"🎉 LEVEL 2! Pizza + 5+ Drawing!"}],"goalLevels":[{"@odata.etag":"","ItemInternalId":"74d188ef-6616-4c2d-bc36-a4cb30eeeee7","Level":"1","Threshold":"35 - Rookie Camp 🏈","Label":"Most New Policies → sm spin","Unlocked":"True"},{"@odata.etag":"","ItemInternalId":"9a9b59ae-38a6-480d-a59a-80e7e1373206","Level":"2a","Threshold":"40 - Combine Star 💪","Label":"➕ Drawing for sm spin (qualify with 5+ new policies, 1 entry per person)","Unlocked":"True"},{"@odata.etag":"","ItemInternalId":"0c76c121-43e6-486f-96ce-d18e94201b34","Level":"2b","Threshold":"40 - Draft Party Pizza 🍕","Label":"➕ Pizza for the Office","Unlocked":"True"},{"@odata.etag":"","ItemInternalId":"db747582-9809-4de5-b02a-9b0dfc3dbcd4","Level":"3","Threshold":"45 - Top Prospect ⭐","Label":"➕ McDonald's/Chick-Fil-A Breakfast OR Upgraded Lunch","Unlocked":"False"},{"@odata.etag":"","ItemInternalId":"dc4e47ff-6c6e-4e42-91c8-e3dd9ab517d5","Level":"4","Threshold":"50 - Franchise Tag 🏷️","Label":"➕ Drawing for sm spin (anyone who sold a new policy, 1 entry per person)","Unlocked":"False"},{"@odata.etag":"","ItemInternalId":"6a3161bd-1abb-4118-828e-895e4b2387e0","Level":"5","Threshold":"55 - GOAT Status 🐐","Label":"ALL OF THE ABOVE ➕ Most New gets 🎗️🎗️🎗️LARGE SPIN 🎰 (replaces sm spin)","Unlocked":"False"}],"weeklyAgentBreakdown":[{"@odata.etag":"","ItemInternalId":"4afcbb00-c24c-49a4-8372-8043ec5cb60f","Rank":"","Agent":"Mary","Policies":"0","Premium":"0"},{"@odata.etag":"","ItemInternalId":"454a2b6b-9508-4f50-bbb4-9707ad720db7","Rank":"1","Agent":"Nesida","Policies":"16","Premium":"38272.52"},{"@odata.etag":"","ItemInternalId":"dd041ed4-fa93-4d93-b7ae-562a60b0b5ea","Rank":"2","Agent":"Austin","Policies":"11","Premium":"26271.02"},{"@odata.etag":"","ItemInternalId":"86f531c7-b97f-435d-b722-feb0f1846250","Rank":"3","Agent":"Gaby","Policies":"6","Premium":"42673.37"},{"@odata.etag":"","ItemInternalId":"97669d43-7401-405f-b5f4-e03a13e743a4","Rank":"6","Agent":"Richar","Policies":"1","Premium":"679"},{"@odata.etag":"","ItemInternalId":"fca1a265-3160-4698-9e85-c105b257aeb2","Rank":"4","Agent":"Isaac","Policies":"5","Premium":"6959.82"},{"@odata.etag":"","ItemInternalId":"6cb18296-87d6-4459-a422-0f3a8344bc64","Rank":"5","Agent":"Richard L","Policies":"2","Premium":"6289"},{"@odata.etag":"","ItemInternalId":"1d339b77-45cf-49e9-ae88-6badd3033e86","Rank":"","Agent":"Keylis","Policies":"0","Premium":"0"}],"drawings":[{"@odata.etag":"","ItemInternalId":"0c7e37a5-393f-4609-aa44-60d0f82ad55c","Type":"📋 5+ POLICIES DRAWING (Unlocks at Level 2a ➡️ 40 policies)","Locked":"","Required":"","Agent":"✅ UNLOCKED -  agent(s) qualify for drawing!"},{"@odata.etag":"","ItemInternalId":"37778197-b446-4535-a6e8-55b2f183f61b","Type":"fivePlus","Locked":"True","Required":"40","Agent":"Mary"},{"@odata.etag":"","ItemInternalId":"e9c457b3-68db-4821-b9f7-01ff25ea7e7d","Type":"fivePlus","Locked":"False","Required":"40","Agent":"Nesida"},{"@odata.etag":"","ItemInternalId":"a484fc71-8621-48ba-8ecd-0921ffcb8fd1","Type":"fivePlus","Locked":"False","Required":"40","Agent":"Austin"},{"@odata.etag":"","ItemInternalId":"17b06ab3-5073-4c6b-afa6-dedc7a3463e0","Type":"fivePlus","Locked":"False","Required":"40","Agent":"Gaby"},{"@odata.etag":"","ItemInternalId":"380c9042-945e-4968-beb5-863a92357b62","Type":"fivePlus","Locked":"True","Required":"40","Agent":"Richar"},{"@odata.etag":"","ItemInternalId":"ec388ce7-1ef6-40d8-91b0-c10af49d1be4","Type":"fivePlus","Locked":"False","Required":"40","Agent":"Isaac"},{"@odata.etag":"","ItemInternalId":"3e59baa4-cacb-46c4-b9f5-0b0572478dd7","Type":"fivePlus","Locked":"True","Required":"40","Agent":"Richard L"},{"@odata.etag":"","ItemInternalId":"a2f015d3-d8f8-473b-85c3-686fad1263e4","Type":"fivePlus","Locked":"True","Required":"40","Agent":"Keylis"},{"@odata.etag":"","ItemInternalId":"c8eacd3b-7097-43b6-95a4-6e0900ea9f81","Type":"📋 1+ POLICIES DRAWING (Unlocks at Level 4 ➡️ 50 policies)","Locked":"","Required":"","Agent":"❌ LOCKED - Need 9 more policies to unlock"},{"@odata.etag":"","ItemInternalId":"4dcb87f8-618c-4d96-9129-57817a7ff655","Type":"onePlus","Locked":"True","Required":"50","Agent":"Mary"},{"@odata.etag":"","ItemInternalId":"bc231899-b868-472a-867f-9d0a7647dadc","Type":"onePlus","Locked":"True","Required":"50","Agent":"Nesida"},{"@odata.etag":"","ItemInternalId":"6c764086-9755-4da0-92c5-62a4be7ba645","Type":"onePlus","Locked":"True","Required":"50","Agent":"Austin"},{"@odata.etag":"","ItemInternalId":"c54ae63b-6f72-4bd8-8557-6ab9adf6500e","Type":"onePlus","Locked":"True","Required":"50","Agent":"Gaby"},{"@odata.etag":"","ItemInternalId":"889791c3-33c4-450d-8094-eb94c1517887","Type":"onePlus","Locked":"True","Required":"50","Agent":"Richar"},{"@odata.etag":"","ItemInternalId":"3bf4ada7-19c0-411c-b52e-8bc5a9fc068d","Type":"onePlus","Locked":"True","Required":"50","Agent":"Isaac"},{"@odata.etag":"","ItemInternalId":"877e66ed-5776-43d6-83c4-5a8ba5d645a3","Type":"onePlus","Locked":"True","Required":"50","Agent":"Richard L"},{"@odata.etag":"","ItemInternalId":"84f95f12-bc33-4d33-821d-e2f259dedd79","Type":"onePlus","Locked":"True","Required":"50","Agent":"Keylis"}]}