{"meta":{"source":"Goals Dashboard Source","lastUpdated":"2026-05-11T03:41:32.2314873Z"},"monthlyNewPremium":[{"@odata.etag":"","ItemInternalId":"4fe15f3f-c7b3-4ed5-bc01-82ec7fc1c7c3","Agent":"Mary","Amount":"0"},{"@odata.etag":"","ItemInternalId":"9d610f55-28e5-47fb-92c4-0affde6cd88c","Agent":"Nesida","Amount":"40438.4"},{"@odata.etag":"","ItemInternalId":"47106e2e-013f-4b8d-9747-2e8ff56a7bab","Agent":"Austin","Amount":"21707.83"},{"@odata.etag":"","ItemInternalId":"2dea4433-dd95-4106-aae0-9ff4d5899f6e","Agent":"Gaby","Amount":"267"},{"@odata.etag":"","ItemInternalId":"fa350a54-6e9a-4ef2-a4f8-de5d77c0f481","Agent":"Richar","Amount":"0"},{"@odata.etag":"","ItemInternalId":"8a6575ac-173c-44f8-a872-e1b568b584e3","Agent":"Isaac","Amount":"654.21"},{"@odata.etag":"","ItemInternalId":"ef17dbe6-385b-4e6b-85f2-f25727d2dd49","Agent":"Richard L","Amount":"0"},{"@odata.etag":"","ItemInternalId":"b00864c5-91c7-42c6-a41d-9134fcd74bc9","Agent":"Total","Amount":"63067.44"}],"weeklyIncentives":[{"@odata.etag":"","ItemInternalId":"883d0417-b717-4648-b403-fad2cb57d7a1","Policies":"23","StatusMessage":"Keep selling... 12 more to Level 1!"}],"goalLevels":[{"@odata.etag":"","ItemInternalId":"09d98500-8c38-4ba3-a46b-6cff72c3c8f3","Level":"1","Threshold":"35 - Activated ⚡","Label":"Most New Policies → sm spin","Unlocked":"False"},{"@odata.etag":"","ItemInternalId":"73b5ef39-c9f5-4b63-8a1b-6e6d5b473f33","Level":"2a","Threshold":"40 - Charged Up 🔋","Label":"➕ Drawing for sm spin (qualify with 5+ new policies, 1 entry per person)","Unlocked":"False"},{"@odata.etag":"","ItemInternalId":"1f755759-ff73-4111-b057-93ed0752d337","Level":"2b","Threshold":"40 - Pizza Power 🍕","Label":"➕ Pizza for the Office","Unlocked":"False"},{"@odata.etag":"","ItemInternalId":"a4f561e8-0b15-4e73-b9c5-15cea5c9e99f","Level":"3","Threshold":"45 - Supercharged ⚡","Label":"➕ McDonald's/Chick-Fil-A Breakfast OR Upgraded Lunch","Unlocked":"False"},{"@odata.etag":"","ItemInternalId":"d762ae76-864f-44a3-a633-3c60cd3de2d2","Level":"4","Threshold":"50 - Overdrive 🚀","Label":"➕ Drawing for sm spin (anyone who sold a new policy, 1 entry per person)","Unlocked":"False"},{"@odata.etag":"","ItemInternalId":"f73d4eb7-8dde-439c-9944-6a84eb9f84dd","Level":"5","Threshold":"55 - Maximum Power 💥","Label":"ALL OF THE ABOVE ➕ Most New gets 🎗️🎗️🎗️LARGE SPIN 🎰 (replaces sm spin)","Unlocked":"False"}],"weeklyAgentBreakdown":[{"@odata.etag":"","ItemInternalId":"32ebb958-63ba-4166-b429-9c86e3071457","Rank":"0","Agent":"Mary","Policies":"0","Premium":"0"},{"@odata.etag":"","ItemInternalId":"7bf2cd3c-6753-49a8-860c-cab397b84acd","Rank":"1","Agent":"Nesida","Policies":"12","Premium":"23330.1"},{"@odata.etag":"","ItemInternalId":"64818dd9-72f8-440a-9faf-e0cc5995428f","Rank":"2","Agent":"Austin","Policies":"11","Premium":"19226.83"},{"@odata.etag":"","ItemInternalId":"19e82903-8603-4149-89d0-855c937fe095","Rank":"0","Agent":"Gaby","Policies":"0","Premium":"0"},{"@odata.etag":"","ItemInternalId":"f8930ab2-aa3b-47a3-9181-83b4a71c4ebb","Rank":"0","Agent":"Richar","Policies":"0","Premium":"0"},{"@odata.etag":"","ItemInternalId":"e5bc9cac-0667-4600-ab0d-ff2794f55834","Rank":"0","Agent":"Isaac","Policies":"0","Premium":"0"},{"@odata.etag":"","ItemInternalId":"78f87196-b141-4bc2-a6c7-f667d90a18de","Rank":"0","Agent":"Richard L","Policies":"0","Premium":"0"}],"drawings":[{"@odata.etag":"","ItemInternalId":"9c69f93e-36ea-4aa0-b02d-4768ecc2b88e","Type":"📋 5+ POLICIES DRAWING (Unlocks at Level 2a ➡️ 40 policies)","Locked":"","Required":"","Agent":"❌ LOCKED - Need 17 more policies to unlock"},{"@odata.etag":"","ItemInternalId":"2efebcb4-d3ed-4fe6-8528-5b30dde25c61","Type":"fivePlus","Locked":"True","Required":"40","Agent":"Mary"},{"@odata.etag":"","ItemInternalId":"a53c9497-5bd6-4a6a-adbb-3650626403f9","Type":"fivePlus","Locked":"True","Required":"40","Agent":"Nesida"},{"@odata.etag":"","ItemInternalId":"5eb03acd-9264-498e-95f7-34d76a42d492","Type":"fivePlus","Locked":"True","Required":"40","Agent":"Austin"},{"@odata.etag":"","ItemInternalId":"d9f38ce1-5222-4ff2-8453-ce209447bcfd","Type":"fivePlus","Locked":"True","Required":"40","Agent":"Gaby"},{"@odata.etag":"","ItemInternalId":"ba96958d-efd7-4715-a2e7-e84f0f20b4c0","Type":"fivePlus","Locked":"True","Required":"40","Agent":"Richar"},{"@odata.etag":"","ItemInternalId":"3ea3abe1-4152-42b7-8a96-2df88b2710e4","Type":"fivePlus","Locked":"True","Required":"40","Agent":"Isaac"},{"@odata.etag":"","ItemInternalId":"e3275d11-932e-4072-9ffe-fe249d21065d","Type":"fivePlus","Locked":"True","Required":"40","Agent":"Richard L"},{"@odata.etag":"","ItemInternalId":"c241fb4b-6524-41e3-ba41-7d67cd16bc67","Type":"📋 1+ POLICIES DRAWING (Unlocks at Level 4 ➡️ 50 policies)","Locked":"","Required":"","Agent":"❌ LOCKED - Need 27 more policies to unlock"},{"@odata.etag":"","ItemInternalId":"3b2fbc9d-1220-462e-b0b5-38f7652b051a","Type":"onePlus","Locked":"True","Required":"50","Agent":"Mary"},{"@odata.etag":"","ItemInternalId":"25c57e0f-1493-4386-a14f-5e000834574f","Type":"onePlus","Locked":"True","Required":"50","Agent":"Nesida"},{"@odata.etag":"","ItemInternalId":"995a7c12-5e8d-4b8c-92cb-6216e972273c","Type":"onePlus","Locked":"True","Required":"50","Agent":"Austin"},{"@odata.etag":"","ItemInternalId":"c88255e8-f6dc-4da4-acf2-f4d1f410ee6c","Type":"onePlus","Locked":"True","Required":"50","Agent":"Gaby"},{"@odata.etag":"","ItemInternalId":"f031104b-f7b9-45eb-9804-4f18d1a291f7","Type":"onePlus","Locked":"True","Required":"50","Agent":"Richar"},{"@odata.etag":"","ItemInternalId":"3c7ef6c1-c1f3-496e-b08c-70aa287eb727","Type":"onePlus","Locked":"True","Required":"50","Agent":"Isaac"},{"@odata.etag":"","ItemInternalId":"9707e5ff-25d3-41fa-88cb-bc2dd2308b6f","Type":"onePlus","Locked":"True","Required":"50","Agent":"Richard L"}]}