{"meta":{"source":"Goals Dashboard Source","lastUpdated":"2026-04-12T10:08:35.1121626Z"},"monthlyNewPremium":[{"@odata.etag":"","ItemInternalId":"0d4ec94b-18ca-4af4-9ef3-9f256c6152f5","Agent":"Mary","Amount":"0"},{"@odata.etag":"","ItemInternalId":"08f1fd71-b505-4aad-a4a3-95e9476169bb","Agent":"Nesida","Amount":"13954.24"},{"@odata.etag":"","ItemInternalId":"f29d9f9f-1586-4fff-b4b3-c2a8510dbe70","Agent":"Austin","Amount":"14913.75"},{"@odata.etag":"","ItemInternalId":"5deb59a1-300e-44b5-8dfc-77207083e4f8","Agent":"Gaby","Amount":"22001.14"},{"@odata.etag":"","ItemInternalId":"0aa1a6e6-bfb4-4f9a-9cf0-cf0256e11af5","Agent":"Richar","Amount":"0"},{"@odata.etag":"","ItemInternalId":"4e66f122-be3c-46fc-9019-689b3eceba30","Agent":"Isaac","Amount":"158"},{"@odata.etag":"","ItemInternalId":"a0b8ef0a-5c82-4211-84df-72f1e0283666","Agent":"Richard L","Amount":"9775.86"},{"@odata.etag":"","ItemInternalId":"91ba379d-0acb-42e4-bb3d-c87f00388b83","Agent":"Keylis","Amount":"8865.39"},{"@odata.etag":"","ItemInternalId":"2bb799f7-727b-46d7-8015-f6019572b706","Agent":"Total","Amount":"69668.38"}],"weeklyIncentives":[{"@odata.etag":"","ItemInternalId":"ae799f24-0f63-454c-8f4f-e5e398821450","Policies":"28","StatusMessage":"Keep selling... 7 more to Level 1!"}],"goalLevels":[{"@odata.etag":"","ItemInternalId":"c6a97453-8142-4095-bc5b-61395e747041","Level":"1","Threshold":"35 - Liftoff 🚀","Label":"Most New Policies → sm spin","Unlocked":"False"},{"@odata.etag":"","ItemInternalId":"58f915bf-19e0-4dad-813b-b48a4351e52a","Level":"2a","Threshold":"40 - Orbit 🛸","Label":"➕ Drawing for sm spin (qualify with 5+ new policies, 1 entry per person)","Unlocked":"False"},{"@odata.etag":"","ItemInternalId":"e1c45594-9907-4d0e-8c62-01ddb7d1551d","Level":"2b","Threshold":"40 - Pizza Planet 🍕","Label":"➕ Pizza for the Office","Unlocked":"False"},{"@odata.etag":"","ItemInternalId":"738bf846-cce1-4789-ba27-f39c253257c7","Level":"3","Threshold":"45 - Warp Speed 💫","Label":"➕ McDonald's/Chick-Fil-A Breakfast OR Upgraded Lunch","Unlocked":"False"},{"@odata.etag":"","ItemInternalId":"cb33327f-9e5b-410c-b47c-5621bb163ac9","Level":"4","Threshold":"50 - Stardom ⭐","Label":"➕ Drawing for sm spin (anyone who sold a new policy, 1 entry per person)","Unlocked":"False"},{"@odata.etag":"","ItemInternalId":"bda81cc6-3952-40f5-a9af-1df54b87f874","Level":"5","Threshold":"55 - Supernova 💥","Label":"ALL OF THE ABOVE ➕ Most New gets 🎗️🎗️🎗️LARGE SPIN 🎰 (replaces sm spin)","Unlocked":"False"}],"weeklyAgentBreakdown":[{"@odata.etag":"","ItemInternalId":"e0e8c3ef-a4f8-4a38-b41e-856dbc21bbe1","Rank":"","Agent":"Mary","Policies":"0","Premium":"0"},{"@odata.etag":"","ItemInternalId":"4d3c645e-8d87-4038-905e-adc76e92c762","Rank":"1","Agent":"Nesida","Policies":"9","Premium":"13954.24"},{"@odata.etag":"","ItemInternalId":"ce77ab4d-b97f-4a52-a0dd-bc0d1da99bcd","Rank":"3","Agent":"Austin","Policies":"7","Premium":"10584"},{"@odata.etag":"","ItemInternalId":"e5c18d84-9bc7-4f09-a817-b8031eb2191c","Rank":"2","Agent":"Gaby","Policies":"7","Premium":"12704.19"},{"@odata.etag":"","ItemInternalId":"fd635065-7b34-47e1-a9f1-462dfe07c0ba","Rank":"","Agent":"Richar","Policies":"0","Premium":"0"},{"@odata.etag":"","ItemInternalId":"904f1c8a-72b8-4136-a76e-d227212c2fa0","Rank":"6","Agent":"Isaac","Policies":"1","Premium":"158"},{"@odata.etag":"","ItemInternalId":"f95455a4-a5c5-44ac-adfe-05bf7d5eacc8","Rank":"4","Agent":"Richard L","Policies":"3","Premium":"6495.2"},{"@odata.etag":"","ItemInternalId":"ade8a252-86e9-46aa-a233-2b5560b600d8","Rank":"5","Agent":"Keylis","Policies":"1","Premium":"5362.77"}],"drawings":[{"@odata.etag":"","ItemInternalId":"709b4ff1-837c-4b9c-ac2c-ce26a14ae34f","Type":"📋 5+ POLICIES DRAWING (Unlocks at Level 2a ➡️ 40 policies)","Locked":"","Required":"","Agent":"❌ LOCKED - Need 12 more policies to unlock"},{"@odata.etag":"","ItemInternalId":"11ce4036-76f3-4699-8b8c-ee1d91eda0fc","Type":"fivePlus","Locked":"True","Required":"40","Agent":"Mary"},{"@odata.etag":"","ItemInternalId":"82269824-b886-4595-ade4-f865f03cfa60","Type":"fivePlus","Locked":"True","Required":"40","Agent":"Nesida"},{"@odata.etag":"","ItemInternalId":"6c026ac4-6a60-46fa-a30a-9f72223a0512","Type":"fivePlus","Locked":"True","Required":"40","Agent":"Austin"},{"@odata.etag":"","ItemInternalId":"0708c6de-08db-43bb-8a1a-0e3378f7a925","Type":"fivePlus","Locked":"True","Required":"40","Agent":"Gaby"},{"@odata.etag":"","ItemInternalId":"14b7caae-8e4a-4475-94c9-e26bdacba06a","Type":"fivePlus","Locked":"True","Required":"40","Agent":"Richar"},{"@odata.etag":"","ItemInternalId":"f82edc8e-2741-4376-a642-7a5daf294932","Type":"fivePlus","Locked":"True","Required":"40","Agent":"Isaac"},{"@odata.etag":"","ItemInternalId":"5d8fae88-7cd6-4f58-92c0-4c6d68355894","Type":"fivePlus","Locked":"True","Required":"40","Agent":"Richard L"},{"@odata.etag":"","ItemInternalId":"01f1c752-caf8-4dc4-bee5-4af3d6d43423","Type":"fivePlus","Locked":"True","Required":"40","Agent":"Keylis"},{"@odata.etag":"","ItemInternalId":"c018e219-ad64-40db-868f-39d2641e394b","Type":"📋 1+ POLICIES DRAWING (Unlocks at Level 4 ➡️ 50 policies)","Locked":"","Required":"","Agent":"❌ LOCKED - Need 22 more policies to unlock"},{"@odata.etag":"","ItemInternalId":"31a1e237-780c-4c3b-be70-a6001da6d32e","Type":"onePlus","Locked":"True","Required":"50","Agent":"Mary"},{"@odata.etag":"","ItemInternalId":"d2aa1744-0f6f-4f56-9425-6c32481d8a75","Type":"onePlus","Locked":"True","Required":"50","Agent":"Nesida"},{"@odata.etag":"","ItemInternalId":"b239cbe0-b7e7-4f50-82a0-25814956b51c","Type":"onePlus","Locked":"True","Required":"50","Agent":"Austin"},{"@odata.etag":"","ItemInternalId":"252fc6eb-8806-465a-abc5-61f73959e05c","Type":"onePlus","Locked":"True","Required":"50","Agent":"Gaby"},{"@odata.etag":"","ItemInternalId":"f21e4003-b5a9-4090-bf51-6b55b45e82d7","Type":"onePlus","Locked":"True","Required":"50","Agent":"Richar"},{"@odata.etag":"","ItemInternalId":"645b2972-6ba9-4c45-8587-05cf4f45f43b","Type":"onePlus","Locked":"True","Required":"50","Agent":"Isaac"},{"@odata.etag":"","ItemInternalId":"ac35f45a-b728-4c15-81bf-49b5048efab2","Type":"onePlus","Locked":"True","Required":"50","Agent":"Richard L"},{"@odata.etag":"","ItemInternalId":"c707f3c1-7095-4437-9c45-ed40859e12fe","Type":"onePlus","Locked":"True","Required":"50","Agent":"Keylis"}]}