{"meta":{"source":"Goals Dashboard Source","lastUpdated":"2026-04-02T11:09:30.5531959Z"},"monthlyNewPremium":[{"@odata.etag":"","ItemInternalId":"87ad99ff-9312-4c3a-b59b-f292c4f45861","Agent":"Mary","Amount":"0"},{"@odata.etag":"","ItemInternalId":"78ca43ea-1e30-4f81-b8a9-d2b803ef97df","Agent":"Nesida","Amount":"98688.16"},{"@odata.etag":"","ItemInternalId":"353407a7-201d-41b1-8602-b90845cff0eb","Agent":"Austin","Amount":"68484.75"},{"@odata.etag":"","ItemInternalId":"06989b06-b4bb-4aba-8146-985d26b16ccf","Agent":"Gaby","Amount":"11978.82"},{"@odata.etag":"","ItemInternalId":"faed94f2-c62b-4e7f-af1e-23f0a30a18fa","Agent":"Richar","Amount":"3310.29"},{"@odata.etag":"","ItemInternalId":"b977197b-f100-46ce-b167-2f7bfe80f7e3","Agent":"Isaac","Amount":"47634.63"},{"@odata.etag":"","ItemInternalId":"8e8ad32a-568b-4969-a242-0de1b4cab807","Agent":"Richard L","Amount":"5464"},{"@odata.etag":"","ItemInternalId":"ea2acc27-763c-4e22-929b-0b8229f90598","Agent":"Keylis","Amount":"13696.09"},{"@odata.etag":"","ItemInternalId":"3481c0a3-3eaa-4819-877f-465fa514cda4","Agent":"Total","Amount":"249256.74"}],"weeklyIncentives":[{"@odata.etag":"","ItemInternalId":"86dd4684-f247-4fa6-9ca8-22e5e922dd16","Policies":"2","StatusMessage":"Keep selling... 33 more to Level 1!"}],"goalLevels":[{"@odata.etag":"","ItemInternalId":"8fe4ae6c-9d99-4ab3-a6f7-cc34dda7a275","Level":"1","Threshold":"35 - Tip-Off 🏀","Label":"Most New Policies → sm spin","Unlocked":"False"},{"@odata.etag":"","ItemInternalId":"63d155ee-9689-4155-8792-0a5424e6cd07","Level":"2a","Threshold":"40 - Fast Break 🏃","Label":"➕ Drawing for sm spin (qualify with 5+ new policies, 1 entry per person)","Unlocked":"False"},{"@odata.etag":"","ItemInternalId":"786880df-ba4a-4126-b713-cd0b513025a5","Level":"2b","Threshold":"40 - Pizza Time-Out 🍕","Label":"➕ Pizza for the Office","Unlocked":"False"},{"@odata.etag":"","ItemInternalId":"451295bd-570e-4de9-8492-336388d04d93","Level":"3","Threshold":"45 - Alley-Oop 🎯","Label":"➕ McDonald's/Chick-Fil-A Breakfast OR Upgraded Lunch","Unlocked":"False"},{"@odata.etag":"","ItemInternalId":"d51369e3-c9c4-4c5d-93ac-6a86f3e6018c","Level":"4","Threshold":"50 - Sweet 16 🏆","Label":"➕ Drawing for sm spin (anyone who sold a new policy, 1 entry per person)","Unlocked":"False"},{"@odata.etag":"","ItemInternalId":"2ef30215-a417-412d-8967-7fb1b5e6f42c","Level":"5","Threshold":"55 - Final Four 🏀🏆","Label":"ALL OF THE ABOVE ➕ Most New gets 🎗️🎗️🎗️LARGE SPIN 🎰 (replaces sm spin)","Unlocked":"False"}],"weeklyAgentBreakdown":[{"@odata.etag":"","ItemInternalId":"ac951622-de0a-458e-9c7f-3d13fd478524","Rank":"","Agent":"Mary","Policies":"0","Premium":"0"},{"@odata.etag":"","ItemInternalId":"4de1d42b-90ea-4c7d-9999-271ea6431217","Rank":"","Agent":"Nesida","Policies":"0","Premium":"0"},{"@odata.etag":"","ItemInternalId":"202648c9-7c71-4b6f-9030-abfc1f8136ad","Rank":"1","Agent":"Austin","Policies":"1","Premium":"1713"},{"@odata.etag":"","ItemInternalId":"5afba35d-d0c5-49e7-a360-c10feb92dfdc","Rank":"","Agent":"Gaby","Policies":"0","Premium":"0"},{"@odata.etag":"","ItemInternalId":"1b2586e0-f8e6-4619-953b-131e6e5ba1e4","Rank":"","Agent":"Richar","Policies":"0","Premium":"0"},{"@odata.etag":"","ItemInternalId":"73d3d547-9452-4154-af5e-1efc904d398a","Rank":"","Agent":"Isaac","Policies":"0","Premium":"0"},{"@odata.etag":"","ItemInternalId":"a352a876-98e9-4989-a5c9-0cb7bfe1efdd","Rank":"","Agent":"Richard L","Policies":"0","Premium":"0"},{"@odata.etag":"","ItemInternalId":"b658b459-b01b-4cea-9db5-4136a5954100","Rank":"2","Agent":"Keylis","Policies":"1","Premium":"1041"}],"drawings":[{"@odata.etag":"","ItemInternalId":"3a71b8f2-2f6e-4861-9257-ee748d23068f","Type":"📋 5+ POLICIES DRAWING (Unlocks at Level 2a ➡️ 40 policies)","Locked":"","Required":"","Agent":"❌ LOCKED - Need 38 more policies to unlock"},{"@odata.etag":"","ItemInternalId":"b26a56d7-8ec8-4a78-8dae-302a68102b82","Type":"fivePlus","Locked":"True","Required":"40","Agent":"Mary"},{"@odata.etag":"","ItemInternalId":"5cc3f3d5-2b98-4e6f-88f0-2429b5259524","Type":"fivePlus","Locked":"True","Required":"40","Agent":"Nesida"},{"@odata.etag":"","ItemInternalId":"44da6562-6af2-4498-9272-e3583211f6b5","Type":"fivePlus","Locked":"True","Required":"40","Agent":"Austin"},{"@odata.etag":"","ItemInternalId":"90195a65-5f90-4145-8649-ff6bfa3d4e71","Type":"fivePlus","Locked":"True","Required":"40","Agent":"Gaby"},{"@odata.etag":"","ItemInternalId":"4f5474e0-9e4e-4479-91a5-a2354f275aea","Type":"fivePlus","Locked":"True","Required":"40","Agent":"Richar"},{"@odata.etag":"","ItemInternalId":"8038fb99-24f9-4f92-92ab-c3f0bc5bd8a5","Type":"fivePlus","Locked":"True","Required":"40","Agent":"Isaac"},{"@odata.etag":"","ItemInternalId":"e27e2099-3282-40fd-be30-fe9f53ca7c7b","Type":"fivePlus","Locked":"True","Required":"40","Agent":"Richard L"},{"@odata.etag":"","ItemInternalId":"4a6ef77a-132d-4e51-bedc-70bf6b308394","Type":"fivePlus","Locked":"True","Required":"40","Agent":"Keylis"},{"@odata.etag":"","ItemInternalId":"b2433cd9-79a4-4e16-bde3-bb553cfcdde0","Type":"📋 1+ POLICIES DRAWING (Unlocks at Level 4 ➡️ 50 policies)","Locked":"","Required":"","Agent":"❌ LOCKED - Need 48 more policies to unlock"},{"@odata.etag":"","ItemInternalId":"01d960d3-8ee0-4e8b-b6be-6f9540e4684a","Type":"onePlus","Locked":"True","Required":"50","Agent":"Mary"},{"@odata.etag":"","ItemInternalId":"afbce228-aca7-48ca-9d86-31918d56da8c","Type":"onePlus","Locked":"True","Required":"50","Agent":"Nesida"},{"@odata.etag":"","ItemInternalId":"e55143f5-0fd9-4113-8480-dbed9f336211","Type":"onePlus","Locked":"True","Required":"50","Agent":"Austin"},{"@odata.etag":"","ItemInternalId":"792a4266-48d9-4826-9397-c80b5a084593","Type":"onePlus","Locked":"True","Required":"50","Agent":"Gaby"},{"@odata.etag":"","ItemInternalId":"147cde1d-79ea-4175-83a5-781151bb06b1","Type":"onePlus","Locked":"True","Required":"50","Agent":"Richar"},{"@odata.etag":"","ItemInternalId":"f0d48f8f-3180-457d-b492-2b6c29c74445","Type":"onePlus","Locked":"True","Required":"50","Agent":"Isaac"},{"@odata.etag":"","ItemInternalId":"4ce0712a-8206-425a-97bd-03f8f900d20b","Type":"onePlus","Locked":"True","Required":"50","Agent":"Richard L"},{"@odata.etag":"","ItemInternalId":"a2b15c5a-8336-4f45-b0db-48d123c343fa","Type":"onePlus","Locked":"True","Required":"50","Agent":"Keylis"}]}