{"meta":{"source":"Goals Dashboard Source","lastUpdated":"2026-04-21T21:18:57.5311649Z"},"monthlyNewPremium":[{"@odata.etag":"","ItemInternalId":"d1a89393-80ae-40f1-9f70-a19bbdca1553","Agent":"Mary","Amount":"0"},{"@odata.etag":"","ItemInternalId":"0f5cea20-c73f-4073-957f-98650cbfec9b","Agent":"Nesida","Amount":"21786.23"},{"@odata.etag":"","ItemInternalId":"a49829d5-4054-48d8-8c19-020a5019da5a","Agent":"Austin","Amount":"26990.14"},{"@odata.etag":"","ItemInternalId":"0ad1daa7-f6fa-407a-9040-d9b262c338d5","Agent":"Gaby","Amount":"22920.14"},{"@odata.etag":"","ItemInternalId":"a3bf171e-cff9-4eaa-9615-47c2d9e25495","Agent":"Richar","Amount":"0"},{"@odata.etag":"","ItemInternalId":"eb3d9d4c-04f2-4f42-ab0d-8795adbebb6e","Agent":"Isaac","Amount":"158"},{"@odata.etag":"","ItemInternalId":"9fbbaced-3e85-43fd-a57e-c22e93756fb4","Agent":"Richard L","Amount":"12450.86"},{"@odata.etag":"","ItemInternalId":"ad0cdc2d-e3ee-4a81-9410-c626b5a533b0","Agent":"Keylis","Amount":"11730.67"},{"@odata.etag":"","ItemInternalId":"524deb53-fe36-4029-b963-806148e8d316","Agent":"Total","Amount":"96036.04"}],"weeklyIncentives":[{"@odata.etag":"","ItemInternalId":"bf033ce6-90e8-4065-bb56-a17e8087b68a","Policies":"11","StatusMessage":"Keep selling... 24 more to Level 1!"}],"goalLevels":[{"@odata.etag":"","ItemInternalId":"872eddff-5b25-48dc-bf60-24c739580982","Level":"1","Threshold":"35 - Liftoff 🚀","Label":"Most New Policies → sm spin","Unlocked":"False"},{"@odata.etag":"","ItemInternalId":"7474d0c3-e372-46fc-8f11-cb55a7bc6f61","Level":"2a","Threshold":"40 - Orbit 🛸","Label":"➕ Drawing for sm spin (qualify with 5+ new policies, 1 entry per person)","Unlocked":"False"},{"@odata.etag":"","ItemInternalId":"e04b98c5-9c00-4072-94a6-5c2368a2c80d","Level":"2b","Threshold":"40 - Pizza Planet 🍕","Label":"➕ Pizza for the Office","Unlocked":"False"},{"@odata.etag":"","ItemInternalId":"d2ed435f-ddb5-41eb-8a2d-67ced316bdb0","Level":"3","Threshold":"45 - Warp Speed 💫","Label":"➕ McDonald's/Chick-Fil-A Breakfast OR Upgraded Lunch","Unlocked":"False"},{"@odata.etag":"","ItemInternalId":"4a713ab1-10be-440f-bdac-5c3f65db1fb0","Level":"4","Threshold":"50 - Stardom ⭐","Label":"➕ Drawing for sm spin (anyone who sold a new policy, 1 entry per person)","Unlocked":"False"},{"@odata.etag":"","ItemInternalId":"bc5c559c-5f25-4c6b-a777-8cb404aa3ff0","Level":"5","Threshold":"55 - Supernova 💥","Label":"ALL OF THE ABOVE ➕ Most New gets 🎗️🎗️🎗️LARGE SPIN 🎰 (replaces sm spin)","Unlocked":"False"}],"weeklyAgentBreakdown":[{"@odata.etag":"","ItemInternalId":"bbddf4cf-4384-44b5-8cfd-504cea76e62f","Rank":"0","Agent":"Mary","Policies":"0","Premium":"0"},{"@odata.etag":"","ItemInternalId":"7a93f74c-4904-4bc2-a094-5ae5200f3414","Rank":"3","Agent":"Nesida","Policies":"2","Premium":"411.039999999999"},{"@odata.etag":"","ItemInternalId":"d89ea028-340c-4064-bed3-cfe2e168a687","Rank":"1","Agent":"Austin","Policies":"4","Premium":"12076.39"},{"@odata.etag":"","ItemInternalId":"23f366dd-ccc7-4958-9294-c89c32ba8a14","Rank":"5","Agent":"Gaby","Policies":"1","Premium":"919"},{"@odata.etag":"","ItemInternalId":"ac7880ef-2b7b-4203-b3e5-c160953df6db","Rank":"0","Agent":"Richar","Policies":"0","Premium":"0"},{"@odata.etag":"","ItemInternalId":"63ff6ba8-bf5e-4f6b-957c-b2342b3420a3","Rank":"0","Agent":"Isaac","Policies":"0","Premium":"0"},{"@odata.etag":"","ItemInternalId":"967cd8e7-a0f1-44ce-9213-11011f7fa6ba","Rank":"4","Agent":"Richard L","Policies":"1","Premium":"2287"},{"@odata.etag":"","ItemInternalId":"862e3256-413b-4086-a0a3-8aa47e24ab23","Rank":"2","Agent":"Keylis","Policies":"3","Premium":"2865.28"}],"drawings":[{"@odata.etag":"","ItemInternalId":"fda39c96-7c01-4586-8518-f5852a6316d0","Type":"📋 5+ POLICIES DRAWING (Unlocks at Level 2a ➡️ 40 policies)","Locked":"","Required":"","Agent":"❌ LOCKED - Need 29 more policies to unlock"},{"@odata.etag":"","ItemInternalId":"6b4257c7-85b3-42ea-a72a-e1cb47475f30","Type":"fivePlus","Locked":"True","Required":"40","Agent":"Mary"},{"@odata.etag":"","ItemInternalId":"bc07a053-4748-49ca-bc9f-f0e9e027057b","Type":"fivePlus","Locked":"True","Required":"40","Agent":"Nesida"},{"@odata.etag":"","ItemInternalId":"b03b0205-f330-4e03-b5fa-65ae70d72835","Type":"fivePlus","Locked":"True","Required":"40","Agent":"Austin"},{"@odata.etag":"","ItemInternalId":"4d61cd05-6f1b-4019-be09-756427887619","Type":"fivePlus","Locked":"True","Required":"40","Agent":"Gaby"},{"@odata.etag":"","ItemInternalId":"25d7e3d8-9a2a-4127-907b-e919993766a4","Type":"fivePlus","Locked":"True","Required":"40","Agent":"Richar"},{"@odata.etag":"","ItemInternalId":"2b38efe4-55f1-4716-9843-f518c0b062f0","Type":"fivePlus","Locked":"True","Required":"40","Agent":"Isaac"},{"@odata.etag":"","ItemInternalId":"c4c9fcb4-baa1-4757-b390-4a7bb57f9c55","Type":"fivePlus","Locked":"True","Required":"40","Agent":"Richard L"},{"@odata.etag":"","ItemInternalId":"227a9a19-4feb-4312-8f4a-0f6b555482c7","Type":"fivePlus","Locked":"True","Required":"40","Agent":"Keylis"},{"@odata.etag":"","ItemInternalId":"b7e9d64b-8241-4144-8ac7-32823583fd4b","Type":"📋 1+ POLICIES DRAWING (Unlocks at Level 4 ➡️ 50 policies)","Locked":"","Required":"","Agent":"❌ LOCKED - Need 39 more policies to unlock"},{"@odata.etag":"","ItemInternalId":"e8fbc352-2506-4bc3-a35c-e2bb8c20f90c","Type":"onePlus","Locked":"True","Required":"50","Agent":"Mary"},{"@odata.etag":"","ItemInternalId":"7861beb4-21ce-4770-b0ef-c03c3967710a","Type":"onePlus","Locked":"True","Required":"50","Agent":"Nesida"},{"@odata.etag":"","ItemInternalId":"8f02723a-1b1a-4575-8cee-718a002c7b22","Type":"onePlus","Locked":"True","Required":"50","Agent":"Austin"},{"@odata.etag":"","ItemInternalId":"7ef69422-6dad-4310-a25d-754303ff0622","Type":"onePlus","Locked":"True","Required":"50","Agent":"Gaby"},{"@odata.etag":"","ItemInternalId":"8b679f26-da06-40ab-9034-f04380a84b57","Type":"onePlus","Locked":"True","Required":"50","Agent":"Richar"},{"@odata.etag":"","ItemInternalId":"c6837f7e-bb90-4e13-9019-8e5d52352a58","Type":"onePlus","Locked":"True","Required":"50","Agent":"Isaac"},{"@odata.etag":"","ItemInternalId":"f5c31974-773f-436f-9fce-c9f0572a7f14","Type":"onePlus","Locked":"True","Required":"50","Agent":"Richard L"},{"@odata.etag":"","ItemInternalId":"63262a32-2ee9-4b60-8b61-9c61549ff785","Type":"onePlus","Locked":"True","Required":"50","Agent":"Keylis"}]}