{"meta":{"source":"Goals Dashboard Source","lastUpdated":"2026-05-04T03:35:26.4072870Z"},"monthlyNewPremium":[{"@odata.etag":"","ItemInternalId":"a5532926-7497-4197-9be0-913fc6b10ce8","Agent":"Mary","Amount":"0"},{"@odata.etag":"","ItemInternalId":"b0ccd4a8-3cd6-463d-8f7e-f20d3d46b3c9","Agent":"Nesida","Amount":"60750.75"},{"@odata.etag":"","ItemInternalId":"bba5f4de-be12-46af-9733-437345c53650","Agent":"Austin","Amount":"53261.16"},{"@odata.etag":"","ItemInternalId":"19399328-787d-4ce1-b99d-2e066195c0c8","Agent":"Gaby","Amount":"66480.51"},{"@odata.etag":"","ItemInternalId":"7d25ac3a-1f18-40fb-867f-dc8fe35d9a54","Agent":"Richar","Amount":"679"},{"@odata.etag":"","ItemInternalId":"7fa04578-e343-4da0-8e8d-9446168b1148","Agent":"Isaac","Amount":"9101.19"},{"@odata.etag":"","ItemInternalId":"988d08eb-7a15-4bbf-806c-a7d212ec5998","Agent":"Richard L","Amount":"21729.86"},{"@odata.etag":"","ItemInternalId":"6634cb13-bd1b-44f3-8249-603fd049c049","Agent":"Keylis","Amount":"11730.67"},{"@odata.etag":"","ItemInternalId":"87f18450-2359-48f6-b9a6-506743548f39","Agent":"Total","Amount":"223733.14"}],"weeklyIncentives":[{"@odata.etag":"","ItemInternalId":"f253c6c0-b038-47f1-8a0c-891d00e17a78","Policies":"41","StatusMessage":"🎉 LEVEL 2! Pizza + 5+ Drawing!"}],"goalLevels":[{"@odata.etag":"","ItemInternalId":"d25a3b2d-732f-4502-8bad-a84367aa2fa9","Level":"1","Threshold":"35 - Rookie Camp 🏈","Label":"Most New Policies → sm spin","Unlocked":"True"},{"@odata.etag":"","ItemInternalId":"956470ef-3f46-4bb6-b8d6-56672a17a265","Level":"2a","Threshold":"40 - Combine Star 💪","Label":"➕ Drawing for sm spin (qualify with 5+ new policies, 1 entry per person)","Unlocked":"True"},{"@odata.etag":"","ItemInternalId":"57f89147-247a-4557-ae7f-053a73544bd9","Level":"2b","Threshold":"40 - Draft Party Pizza 🍕","Label":"➕ Pizza for the Office","Unlocked":"True"},{"@odata.etag":"","ItemInternalId":"3b433102-7fd6-492c-bb52-dcdcf004ea23","Level":"3","Threshold":"45 - Top Prospect ⭐","Label":"➕ McDonald's/Chick-Fil-A Breakfast OR Upgraded Lunch","Unlocked":"False"},{"@odata.etag":"","ItemInternalId":"2da2ac92-d9eb-4d02-ad72-21908bbb8beb","Level":"4","Threshold":"50 - Franchise Tag 🏷️","Label":"➕ Drawing for sm spin (anyone who sold a new policy, 1 entry per person)","Unlocked":"False"},{"@odata.etag":"","ItemInternalId":"a001dca0-eadf-419c-834e-eba80aec2d12","Level":"5","Threshold":"55 - GOAT Status 🐐","Label":"ALL OF THE ABOVE ➕ Most New gets 🎗️🎗️🎗️LARGE SPIN 🎰 (replaces sm spin)","Unlocked":"False"}],"weeklyAgentBreakdown":[{"@odata.etag":"","ItemInternalId":"143bda77-b0b3-4453-bd62-023308e8bab8","Rank":"","Agent":"Mary","Policies":"0","Premium":"0"},{"@odata.etag":"","ItemInternalId":"394f3b31-b47a-43ae-8a06-c34c65d29e2e","Rank":"1","Agent":"Nesida","Policies":"16","Premium":"38272.52"},{"@odata.etag":"","ItemInternalId":"f0a9f39d-2b58-44f6-a31b-dee250fba9e7","Rank":"2","Agent":"Austin","Policies":"11","Premium":"26271.02"},{"@odata.etag":"","ItemInternalId":"b028acff-9c7e-4d8f-96f4-81625257d6e1","Rank":"3","Agent":"Gaby","Policies":"6","Premium":"42673.37"},{"@odata.etag":"","ItemInternalId":"f83aa0b8-b5f7-4110-bc08-a14f2ceae6dd","Rank":"6","Agent":"Richar","Policies":"1","Premium":"679"},{"@odata.etag":"","ItemInternalId":"6c304fd4-497d-429f-a4e1-cf068d74028c","Rank":"4","Agent":"Isaac","Policies":"5","Premium":"6959.82"},{"@odata.etag":"","ItemInternalId":"f2bba17b-d62e-4a70-9b1e-439ce9a71861","Rank":"5","Agent":"Richard L","Policies":"2","Premium":"6289"},{"@odata.etag":"","ItemInternalId":"d5b1af0c-944c-47d9-99da-386a4c38b377","Rank":"","Agent":"Keylis","Policies":"0","Premium":"0"}],"drawings":[{"@odata.etag":"","ItemInternalId":"598ec539-b4ac-4c3f-8af7-8169b4f839ee","Type":"📋 5+ POLICIES DRAWING (Unlocks at Level 2a ➡️ 40 policies)","Locked":"","Required":"","Agent":"✅ UNLOCKED -  agent(s) qualify for drawing!"},{"@odata.etag":"","ItemInternalId":"2c498f49-61ab-4e0f-b525-9823bd3022b6","Type":"fivePlus","Locked":"True","Required":"40","Agent":"Mary"},{"@odata.etag":"","ItemInternalId":"cb6cd075-8539-4fc7-838d-4793463d756d","Type":"fivePlus","Locked":"False","Required":"40","Agent":"Nesida"},{"@odata.etag":"","ItemInternalId":"cbb8c968-96fa-47a3-adb6-5cfcde25b673","Type":"fivePlus","Locked":"False","Required":"40","Agent":"Austin"},{"@odata.etag":"","ItemInternalId":"0b6ec5ad-9807-477e-9201-0a08824c7f23","Type":"fivePlus","Locked":"False","Required":"40","Agent":"Gaby"},{"@odata.etag":"","ItemInternalId":"4421b66a-01eb-4c9d-922b-28780c885f12","Type":"fivePlus","Locked":"True","Required":"40","Agent":"Richar"},{"@odata.etag":"","ItemInternalId":"dd9acf76-2d74-4f39-9f62-04f13ef5dd96","Type":"fivePlus","Locked":"False","Required":"40","Agent":"Isaac"},{"@odata.etag":"","ItemInternalId":"fbce0909-6d20-440f-ad20-ebd626b06675","Type":"fivePlus","Locked":"True","Required":"40","Agent":"Richard L"},{"@odata.etag":"","ItemInternalId":"ff67607a-1b7c-41c4-a260-0bd06d78adda","Type":"fivePlus","Locked":"True","Required":"40","Agent":"Keylis"},{"@odata.etag":"","ItemInternalId":"28c0dc1a-85a6-4619-bd3a-41bed1f57052","Type":"📋 1+ POLICIES DRAWING (Unlocks at Level 4 ➡️ 50 policies)","Locked":"","Required":"","Agent":"❌ LOCKED - Need 9 more policies to unlock"},{"@odata.etag":"","ItemInternalId":"9d6da05b-2cd7-4ba7-8b22-dbcac5cdd044","Type":"onePlus","Locked":"True","Required":"50","Agent":"Mary"},{"@odata.etag":"","ItemInternalId":"65302784-a18f-4d7e-a65a-f09973dd00ba","Type":"onePlus","Locked":"True","Required":"50","Agent":"Nesida"},{"@odata.etag":"","ItemInternalId":"27fb27d5-9db6-43f0-a59b-5318976548c2","Type":"onePlus","Locked":"True","Required":"50","Agent":"Austin"},{"@odata.etag":"","ItemInternalId":"4419293d-4228-45e8-b7b8-57d7113ceffa","Type":"onePlus","Locked":"True","Required":"50","Agent":"Gaby"},{"@odata.etag":"","ItemInternalId":"77f07c0d-4114-4693-b53c-a0e800c1195a","Type":"onePlus","Locked":"True","Required":"50","Agent":"Richar"},{"@odata.etag":"","ItemInternalId":"e089f9a8-8310-4a82-ab9a-288fc6838fdb","Type":"onePlus","Locked":"True","Required":"50","Agent":"Isaac"},{"@odata.etag":"","ItemInternalId":"18281021-0a80-4649-875c-01dbc6f253e8","Type":"onePlus","Locked":"True","Required":"50","Agent":"Richard L"},{"@odata.etag":"","ItemInternalId":"646e61bf-b7d2-4985-b80c-943aad2efc2f","Type":"onePlus","Locked":"True","Required":"50","Agent":"Keylis"}]}