{"meta":{"source":"Goals Dashboard Source","lastUpdated":"2026-05-13T00:25:29.5306038Z"},"monthlyNewPremium":[{"@odata.etag":"","ItemInternalId":"d7513a52-d80f-4511-a8ea-013e28213704","Agent":"Mary","Amount":"0"},{"@odata.etag":"","ItemInternalId":"5b2dace2-8aa3-4f03-9ea2-ad200835b09a","Agent":"Nesida","Amount":"40438.4"},{"@odata.etag":"","ItemInternalId":"408212f9-f3bf-4c7c-8faf-54b05b460669","Agent":"Austin","Amount":"21707.83"},{"@odata.etag":"","ItemInternalId":"3f323725-268d-4f74-b4dc-505bc88cc9f3","Agent":"Gaby","Amount":"267"},{"@odata.etag":"","ItemInternalId":"c74543f1-af4f-4754-a2c9-527e58f49195","Agent":"Richar","Amount":"0"},{"@odata.etag":"","ItemInternalId":"fc9c459b-05f2-4caa-976c-e73371358e7c","Agent":"Isaac","Amount":"654.21"},{"@odata.etag":"","ItemInternalId":"ab3500ef-139c-49c2-bc01-c5cd65e28c7d","Agent":"Richard L","Amount":"0"},{"@odata.etag":"","ItemInternalId":"2e84593b-44a6-4738-b31a-c87f0dfe6d02","Agent":"Total","Amount":"63067.44"}],"weeklyIncentives":[{"@odata.etag":"","ItemInternalId":"eb52cc56-ac66-4564-ae19-09e55b50984f","Policies":"23","StatusMessage":"Keep selling... 12 more to Level 1!"}],"goalLevels":[{"@odata.etag":"","ItemInternalId":"2f6456cd-943b-4ad5-800a-77c2814db032","Level":"1","Threshold":"35 - Activated ⚡","Label":"Most New Policies → sm spin","Unlocked":"False"},{"@odata.etag":"","ItemInternalId":"4d5eb5a2-897d-495b-a42e-68be3e824b88","Level":"2a","Threshold":"40 - Charged Up 🔋","Label":"➕ Drawing for sm spin (qualify with 5+ new policies, 1 entry per person)","Unlocked":"False"},{"@odata.etag":"","ItemInternalId":"b38a28c8-82c3-4549-aa10-89dedc42c602","Level":"2b","Threshold":"40 - Pizza Power 🍕","Label":"➕ Pizza for the Office","Unlocked":"False"},{"@odata.etag":"","ItemInternalId":"c9621d96-3a37-4d6c-b443-2647554e6443","Level":"3","Threshold":"45 - Supercharged ⚡","Label":"➕ McDonald's/Chick-Fil-A Breakfast OR Upgraded Lunch","Unlocked":"False"},{"@odata.etag":"","ItemInternalId":"66250e8d-e917-4d37-9070-59ea6b237596","Level":"4","Threshold":"50 - Overdrive 🚀","Label":"➕ Drawing for sm spin (anyone who sold a new policy, 1 entry per person)","Unlocked":"False"},{"@odata.etag":"","ItemInternalId":"a7dd8465-af90-4c81-bed9-cf752605df1e","Level":"5","Threshold":"55 - Maximum Power 💥","Label":"ALL OF THE ABOVE ➕ Most New gets 🎗️🎗️🎗️LARGE SPIN 🎰 (replaces sm spin)","Unlocked":"False"}],"weeklyAgentBreakdown":[{"@odata.etag":"","ItemInternalId":"2f189b19-be10-4623-8787-9f880752d105","Rank":"0","Agent":"Mary","Policies":"0","Premium":"0"},{"@odata.etag":"","ItemInternalId":"620fae15-3af9-4017-aeba-1f8c6e3fafda","Rank":"1","Agent":"Nesida","Policies":"12","Premium":"23330.1"},{"@odata.etag":"","ItemInternalId":"76bab71a-8eea-407b-9bdb-76165cd0651a","Rank":"2","Agent":"Austin","Policies":"11","Premium":"19226.83"},{"@odata.etag":"","ItemInternalId":"9162de83-4b98-4926-a07e-e8d31fcd7dff","Rank":"0","Agent":"Gaby","Policies":"0","Premium":"0"},{"@odata.etag":"","ItemInternalId":"a083e179-426d-45d6-95da-693b0c242391","Rank":"0","Agent":"Richar","Policies":"0","Premium":"0"},{"@odata.etag":"","ItemInternalId":"d9cc3b08-c437-424a-b77f-c349f35f506c","Rank":"0","Agent":"Isaac","Policies":"0","Premium":"0"},{"@odata.etag":"","ItemInternalId":"b0fc4439-683d-4f69-9a51-7b36be222242","Rank":"0","Agent":"Richard L","Policies":"0","Premium":"0"}],"drawings":[{"@odata.etag":"","ItemInternalId":"d084c606-c636-4b21-a418-74913be7d538","Type":"📋 5+ POLICIES DRAWING (Unlocks at Level 2a ➡️ 40 policies)","Locked":"","Required":"","Agent":"❌ LOCKED - Need 17 more policies to unlock"},{"@odata.etag":"","ItemInternalId":"1949f840-a772-459f-b234-4fddc798ded8","Type":"fivePlus","Locked":"True","Required":"40","Agent":"Mary"},{"@odata.etag":"","ItemInternalId":"186b0e1c-c436-4f67-b677-2108d3bc3bbe","Type":"fivePlus","Locked":"True","Required":"40","Agent":"Nesida"},{"@odata.etag":"","ItemInternalId":"664c939c-69d0-4852-a2b9-61a2bbdd690c","Type":"fivePlus","Locked":"True","Required":"40","Agent":"Austin"},{"@odata.etag":"","ItemInternalId":"5983b7ed-b109-464e-9fbb-ce0306a0f5ea","Type":"fivePlus","Locked":"True","Required":"40","Agent":"Gaby"},{"@odata.etag":"","ItemInternalId":"5d39898f-2f4b-4179-a576-49c7e4c60061","Type":"fivePlus","Locked":"True","Required":"40","Agent":"Richar"},{"@odata.etag":"","ItemInternalId":"671ec0ac-b8a0-4afa-affb-fac2acba0a21","Type":"fivePlus","Locked":"True","Required":"40","Agent":"Isaac"},{"@odata.etag":"","ItemInternalId":"e7ab2d5b-23d0-472f-8c62-9ec3435aef86","Type":"fivePlus","Locked":"True","Required":"40","Agent":"Richard L"},{"@odata.etag":"","ItemInternalId":"a1ed3693-5cb1-40f7-bbcd-33fc88d867c1","Type":"📋 1+ POLICIES DRAWING (Unlocks at Level 4 ➡️ 50 policies)","Locked":"","Required":"","Agent":"❌ LOCKED - Need 27 more policies to unlock"},{"@odata.etag":"","ItemInternalId":"40e1be09-eb70-4e8d-8ad7-204f61e6ce7c","Type":"onePlus","Locked":"True","Required":"50","Agent":"Mary"},{"@odata.etag":"","ItemInternalId":"6aee7ec9-26ae-4f13-9b1d-5a946e7946cf","Type":"onePlus","Locked":"True","Required":"50","Agent":"Nesida"},{"@odata.etag":"","ItemInternalId":"dc8fac89-53f5-4d9f-bcba-6aff3817517f","Type":"onePlus","Locked":"True","Required":"50","Agent":"Austin"},{"@odata.etag":"","ItemInternalId":"c16bd03f-5bf7-43eb-bebd-5d2590aa4b6d","Type":"onePlus","Locked":"True","Required":"50","Agent":"Gaby"},{"@odata.etag":"","ItemInternalId":"c49b486c-56cc-4cca-9d20-0f5faf323c3c","Type":"onePlus","Locked":"True","Required":"50","Agent":"Richar"},{"@odata.etag":"","ItemInternalId":"9900ce6b-b643-4ee4-a29c-3d25207bbc20","Type":"onePlus","Locked":"True","Required":"50","Agent":"Isaac"},{"@odata.etag":"","ItemInternalId":"7a6a92fd-25d7-4fa4-9a3a-f50f18258e5b","Type":"onePlus","Locked":"True","Required":"50","Agent":"Richard L"}]}