{"meta":{"source":"Goals Dashboard Source","lastUpdated":"2026-03-24T10:44:20.0274399Z"},"monthlyNewPremium":[{"@odata.etag":"","ItemInternalId":"2ad03279-026f-4377-8308-3faf21f8bbd4","Agent":"Mary","Amount":"0"},{"@odata.etag":"","ItemInternalId":"a3079d72-7880-4649-aff7-cb2763e232f2","Agent":"Nesida","Amount":"78790.33"},{"@odata.etag":"","ItemInternalId":"9d053025-b968-4f0c-b9b0-8552931df94c","Agent":"Austin","Amount":"63393.9"},{"@odata.etag":"","ItemInternalId":"8f93efa8-061a-463d-aa27-3a8657eccbfa","Agent":"Gaby","Amount":"10947.88"},{"@odata.etag":"","ItemInternalId":"d58cfcdf-d4a4-412f-b0c6-9f0cb90b9571","Agent":"Richar","Amount":"3310.29"},{"@odata.etag":"","ItemInternalId":"95022a9d-1137-459b-a9a9-f028f5126d30","Agent":"Isaac","Amount":"33587.38"},{"@odata.etag":"","ItemInternalId":"1bcc3a6c-edd7-47b2-a105-8e127ab1c13f","Agent":"Richard L","Amount":"3452"},{"@odata.etag":"","ItemInternalId":"b043b396-f1c7-4786-84b0-4da92ae5a53a","Agent":"Keylis","Amount":"10752.09"}],"weeklyIncentives":[{"@odata.etag":"","ItemInternalId":"2b8efce5-bc02-4d31-a17a-1a90f59f349b","Policies":"8","StatusMessage":"Keep selling... 27 more to Level 1!"}],"goalLevels":[{"@odata.etag":"","ItemInternalId":"99ecf22b-929e-44e2-8d3e-5c5e203f5653","Level":"1","Threshold":"35 - Tip-Off 🏀","Label":"Most New Policies → sm spin","Unlocked":"False"},{"@odata.etag":"","ItemInternalId":"d1fd0f3e-4bd7-4bf4-a711-0c1b6d7ede30","Level":"2a","Threshold":"40 - Fast Break 🏃","Label":"➕ Drawing for sm spin (qualify with 5+ new policies)","Unlocked":"False"},{"@odata.etag":"","ItemInternalId":"2238b34f-7d8e-4a48-be65-65ef2170210a","Level":"2b","Threshold":"40 - Pizza Time-Out 🍕","Label":"➕ Pizza for the Office","Unlocked":"False"},{"@odata.etag":"","ItemInternalId":"244c0d93-afb6-4810-889a-fa70ada14920","Level":"3","Threshold":"45 - Alley-Oop 🎯","Label":"➕ McDonald's/Chick-Fil-A Breakfast OR Upgraded Lunch","Unlocked":"False"},{"@odata.etag":"","ItemInternalId":"e6b2c641-441e-4291-bf2b-22edaae5d688","Level":"4","Threshold":"50 - Sweet 16 🏆","Label":"➕ Drawing for sm spin (anyone who sold a new policy)","Unlocked":"False"},{"@odata.etag":"","ItemInternalId":"77853e65-e4ba-4c48-b06a-f4f219a2dc31","Level":"5","Threshold":"55 - Final Four 🏀🏆","Label":"ALL OF THE ABOVE ➕ Most New gets 🎗️🎗️🎗️LARGE SPIN 🎰 (replaces sm spin)","Unlocked":"False"}],"weeklyAgentBreakdown":[{"@odata.etag":"","ItemInternalId":"56dd85f2-08ef-4aa6-a7ab-6ddfdfc665fb","Rank":"","Agent":"Mary","Policies":"0","Premium":"0"},{"@odata.etag":"","ItemInternalId":"00163352-027d-4227-b96c-45d58fcc1f84","Rank":"1","Agent":"Nesida","Policies":"3","Premium":"8206.81"},{"@odata.etag":"","ItemInternalId":"0248f34f-a71e-4f61-8122-1544700fe430","Rank":"2","Agent":"Austin","Policies":"2","Premium":"2638.01"},{"@odata.etag":"","ItemInternalId":"80ce793a-d0b8-4bfa-9911-244280f4d911","Rank":"3","Agent":"Gaby","Policies":"1","Premium":"1673.3"},{"@odata.etag":"","ItemInternalId":"99053c75-b720-4fdb-966b-89a75ad0d273","Rank":"","Agent":"Richar","Policies":"0","Premium":"0"},{"@odata.etag":"","ItemInternalId":"9ac9f029-0570-4b12-8682-a4cb17b71d33","Rank":"5","Agent":"Isaac","Policies":"1","Premium":"1263"},{"@odata.etag":"","ItemInternalId":"60d8dc2f-0548-4153-bba4-114709b7071a","Rank":"","Agent":"Richard L","Policies":"0","Premium":"0"},{"@odata.etag":"","ItemInternalId":"ff9ffad7-3445-4357-8b96-fa2895318ba0","Rank":"4","Agent":"Keylis","Policies":"1","Premium":"1347"}],"drawings":[{"@odata.etag":"","ItemInternalId":"2d37d08e-ed1f-4630-875e-6396ca699f49","Type":"📋 5+ POLICIES DRAWING (Unlocks at Level 2a ➡️ 40 policies)","Locked":"","Required":"","Agent":"❌ LOCKED - Need 32 more policies to unlock"},{"@odata.etag":"","ItemInternalId":"4304fba1-c45c-4c03-ab50-354eb9d15dad","Type":"fivePlus","Locked":"True","Required":"40","Agent":"Mary"},{"@odata.etag":"","ItemInternalId":"1a509a94-7e8f-4cdc-b0d4-06f57f724745","Type":"fivePlus","Locked":"True","Required":"40","Agent":"Nesida"},{"@odata.etag":"","ItemInternalId":"0e9e7d0f-33e4-46f0-8e47-25512d18e5b9","Type":"fivePlus","Locked":"True","Required":"40","Agent":"Austin"},{"@odata.etag":"","ItemInternalId":"b617fcd4-6748-4979-a0e5-36f44646861f","Type":"fivePlus","Locked":"True","Required":"40","Agent":"Gaby"},{"@odata.etag":"","ItemInternalId":"89dd38cc-dd5a-4f57-9f1a-018c16aa5c92","Type":"fivePlus","Locked":"True","Required":"40","Agent":"Richar"},{"@odata.etag":"","ItemInternalId":"7744a770-71ce-4d71-9328-d2fc72006192","Type":"fivePlus","Locked":"True","Required":"40","Agent":"Isaac"},{"@odata.etag":"","ItemInternalId":"729e2de6-5883-4277-8d6d-0c5a0de152b6","Type":"fivePlus","Locked":"True","Required":"40","Agent":"Richard L"},{"@odata.etag":"","ItemInternalId":"20413b13-d323-4dcf-ab54-ffa220f62940","Type":"fivePlus","Locked":"True","Required":"40","Agent":"Keylis"},{"@odata.etag":"","ItemInternalId":"2ca702c4-6ccf-40c6-ac72-7f6ea2e25427","Type":"📋 1+ POLICIES DRAWING (Unlocks at Level 4 ➡️ 50 policies)","Locked":"","Required":"","Agent":"❌ LOCKED - Need 42 more policies to unlock"},{"@odata.etag":"","ItemInternalId":"94615f5f-45d8-4038-a976-99b69ec22d58","Type":"onePlus","Locked":"True","Required":"50","Agent":"Mary"},{"@odata.etag":"","ItemInternalId":"39aab6c6-fd8b-4045-9557-c6f90065d92e","Type":"onePlus","Locked":"True","Required":"50","Agent":"Nesida"},{"@odata.etag":"","ItemInternalId":"e74b04c0-640c-4de9-a80b-c5c11c9e8daf","Type":"onePlus","Locked":"True","Required":"50","Agent":"Austin"},{"@odata.etag":"","ItemInternalId":"b76a73ee-c442-4d6a-badf-792f55c0e4c0","Type":"onePlus","Locked":"True","Required":"50","Agent":"Gaby"},{"@odata.etag":"","ItemInternalId":"22c71845-8c0f-43c4-a8ae-9714d95a61c2","Type":"onePlus","Locked":"True","Required":"50","Agent":"Richar"},{"@odata.etag":"","ItemInternalId":"553dd46f-372c-4866-b0b2-efd9c87f8539","Type":"onePlus","Locked":"True","Required":"50","Agent":"Isaac"},{"@odata.etag":"","ItemInternalId":"a6cbdac5-b4b8-4e9a-b204-b3126301a6cf","Type":"onePlus","Locked":"True","Required":"50","Agent":"Richard L"},{"@odata.etag":"","ItemInternalId":"45eee7c3-4f43-4644-a2b1-6db2caaef506","Type":"onePlus","Locked":"True","Required":"50","Agent":"Keylis"}]}