{"meta":{"source":"Goals Dashboard Source","lastUpdated":"2026-04-08T18:19:47.2124533Z"},"monthlyNewPremium":[{"@odata.etag":"","ItemInternalId":"c7f941f2-144b-4926-935e-3b4643482708","Agent":"Mary","Amount":"0"},{"@odata.etag":"","ItemInternalId":"0d39479d-0be4-4313-89e7-51fdd09e8ee2","Agent":"Nesida","Amount":"2186.96"},{"@odata.etag":"","ItemInternalId":"bbae1b0c-94ea-4bfc-853c-fae80449351d","Agent":"Austin","Amount":"6905.75"},{"@odata.etag":"","ItemInternalId":"023f8a5c-9b92-48b3-b042-d1cbd63bb4ed","Agent":"Gaby","Amount":"17095.53"},{"@odata.etag":"","ItemInternalId":"5fb0204b-2f17-444c-ac6e-7f7109487c36","Agent":"Richar","Amount":"0"},{"@odata.etag":"","ItemInternalId":"08159fde-1795-4208-b50c-e470162a6e9f","Agent":"Isaac","Amount":"158"},{"@odata.etag":"","ItemInternalId":"7cf15787-4b68-49fa-bd4a-5dda2dc26bbb","Agent":"Richard L","Amount":"3280.66"},{"@odata.etag":"","ItemInternalId":"5ada15af-c5d4-41a7-bd04-f3cb3766e0c8","Agent":"Keylis","Amount":"10274.39"},{"@odata.etag":"","ItemInternalId":"b5609c1c-8528-4b70-8d31-2876e0b217c8","Agent":"Total","Amount":"39901.29"}],"weeklyIncentives":[{"@odata.etag":"","ItemInternalId":"855c8333-4c51-4bb3-a411-49fe84dbe6e5","Policies":"14","StatusMessage":"Keep selling... 21 more to Level 1!"}],"goalLevels":[{"@odata.etag":"","ItemInternalId":"6256ff1e-d0ad-4138-ab24-2a29f1b4c861","Level":"1","Threshold":"35 - Tip-Off 🏀","Label":"Most New Policies → sm spin","Unlocked":"False"},{"@odata.etag":"","ItemInternalId":"8f6e1548-e4ae-4655-8954-9522c5a80881","Level":"2a","Threshold":"40 - Fast Break 🏃","Label":"➕ Drawing for sm spin (qualify with 5+ new policies, 1 entry per person)","Unlocked":"False"},{"@odata.etag":"","ItemInternalId":"33de8d20-aefa-41b0-ac71-9edaf7fbc130","Level":"2b","Threshold":"40 - Pizza Time-Out 🍕","Label":"➕ Pizza for the Office","Unlocked":"False"},{"@odata.etag":"","ItemInternalId":"89b72273-30c6-45e1-a8b3-e676fe6fe05a","Level":"3","Threshold":"45 - Alley-Oop 🎯","Label":"➕ McDonald's/Chick-Fil-A Breakfast OR Upgraded Lunch","Unlocked":"False"},{"@odata.etag":"","ItemInternalId":"eead8763-af6a-4820-b67c-8b2e80f71777","Level":"4","Threshold":"50 - Sweet 16 🏆","Label":"➕ Drawing for sm spin (anyone who sold a new policy, 1 entry per person)","Unlocked":"False"},{"@odata.etag":"","ItemInternalId":"33566ea4-1072-47ea-a00a-07faf236d3af","Level":"5","Threshold":"55 - Final Four 🏀🏆","Label":"ALL OF THE ABOVE ➕ Most New gets 🎗️🎗️🎗️LARGE SPIN 🎰 (replaces sm spin)","Unlocked":"False"}],"weeklyAgentBreakdown":[{"@odata.etag":"","ItemInternalId":"c5e1adc1-2941-442f-a599-2e0dd00232be","Rank":"","Agent":"Mary","Policies":"0","Premium":"0"},{"@odata.etag":"","ItemInternalId":"c8e62def-dcdf-4a3d-ae25-269105ecf3ac","Rank":"5","Agent":"Nesida","Policies":"2","Premium":"2186.96"},{"@odata.etag":"","ItemInternalId":"76bbf520-c511-4448-83b7-7a0833505671","Rank":"2","Agent":"Austin","Policies":"3","Premium":"2576"},{"@odata.etag":"","ItemInternalId":"e43e2be7-4a41-4104-b708-fff2e3d19273","Rank":"1","Agent":"Gaby","Policies":"4","Premium":"7798.58"},{"@odata.etag":"","ItemInternalId":"9afdd758-1212-4879-98a0-5b9c369b8621","Rank":"","Agent":"Richar","Policies":"0","Premium":"0"},{"@odata.etag":"","ItemInternalId":"536bae46-223c-4301-8b57-414ed9107ca1","Rank":"6","Agent":"Isaac","Policies":"1","Premium":"158"},{"@odata.etag":"","ItemInternalId":"9fd9211d-cb70-4ef3-bfdc-f201b6775631","Rank":"4","Agent":"Richard L","Policies":"2","Premium":"5337"},{"@odata.etag":"","ItemInternalId":"9dd48dd8-c2b4-4c77-a042-5b5d7758c26e","Rank":"3","Agent":"Keylis","Policies":"2","Premium":"6771.77"}],"drawings":[{"@odata.etag":"","ItemInternalId":"b9117bd0-6c78-407e-9b44-7109ab0fccf6","Type":"📋 5+ POLICIES DRAWING (Unlocks at Level 2a ➡️ 40 policies)","Locked":"","Required":"","Agent":"❌ LOCKED - Need 26 more policies to unlock"},{"@odata.etag":"","ItemInternalId":"0be2f2ee-5b70-4e98-9d8e-48651928d2b9","Type":"fivePlus","Locked":"True","Required":"40","Agent":"Mary"},{"@odata.etag":"","ItemInternalId":"9914b6c9-8aa3-4553-b759-8811b2775991","Type":"fivePlus","Locked":"True","Required":"40","Agent":"Nesida"},{"@odata.etag":"","ItemInternalId":"396d2317-2287-42c4-9d16-eced06193339","Type":"fivePlus","Locked":"True","Required":"40","Agent":"Austin"},{"@odata.etag":"","ItemInternalId":"e0916430-d3df-48af-957a-9f103a31c851","Type":"fivePlus","Locked":"True","Required":"40","Agent":"Gaby"},{"@odata.etag":"","ItemInternalId":"871d9c23-9ef9-4655-9baf-d9b09923d2b7","Type":"fivePlus","Locked":"True","Required":"40","Agent":"Richar"},{"@odata.etag":"","ItemInternalId":"ff5c3123-7281-4cac-939e-76d56353d87e","Type":"fivePlus","Locked":"True","Required":"40","Agent":"Isaac"},{"@odata.etag":"","ItemInternalId":"afdb5d9d-ae34-463b-851e-d2b12160811c","Type":"fivePlus","Locked":"True","Required":"40","Agent":"Richard L"},{"@odata.etag":"","ItemInternalId":"b8579886-c63d-47e1-a7b1-348ec31128de","Type":"fivePlus","Locked":"True","Required":"40","Agent":"Keylis"},{"@odata.etag":"","ItemInternalId":"34eb54af-8b92-4dee-bd6b-1bf86e07dbc0","Type":"📋 1+ POLICIES DRAWING (Unlocks at Level 4 ➡️ 50 policies)","Locked":"","Required":"","Agent":"❌ LOCKED - Need 36 more policies to unlock"},{"@odata.etag":"","ItemInternalId":"f4fc7ac3-329c-4dc4-b32a-a5f299d29050","Type":"onePlus","Locked":"True","Required":"50","Agent":"Mary"},{"@odata.etag":"","ItemInternalId":"f7cba314-5f8e-4b67-8b9e-4dc752861fc7","Type":"onePlus","Locked":"True","Required":"50","Agent":"Nesida"},{"@odata.etag":"","ItemInternalId":"e8eef7a7-7a54-4ec4-867f-cd4d03003910","Type":"onePlus","Locked":"True","Required":"50","Agent":"Austin"},{"@odata.etag":"","ItemInternalId":"190d45a5-b608-4d8a-8881-df69113cfea6","Type":"onePlus","Locked":"True","Required":"50","Agent":"Gaby"},{"@odata.etag":"","ItemInternalId":"45969dbb-7473-4dd2-b2e2-5212d2c97e74","Type":"onePlus","Locked":"True","Required":"50","Agent":"Richar"},{"@odata.etag":"","ItemInternalId":"19609ab5-09ba-4f97-9e6d-c0ed98258f0b","Type":"onePlus","Locked":"True","Required":"50","Agent":"Isaac"},{"@odata.etag":"","ItemInternalId":"febd9045-e05d-4d3a-aed1-d5b64baddb8c","Type":"onePlus","Locked":"True","Required":"50","Agent":"Richard L"},{"@odata.etag":"","ItemInternalId":"7fa169fa-9fcc-4c5a-8047-81190d5e9db0","Type":"onePlus","Locked":"True","Required":"50","Agent":"Keylis"}]}